.gitignore
.pre-commit-config.yaml
LICENSE
MANIFEST.in
README.md
memo_deploy.md
pyproject.toml
requirements.txt
setup.cfg
setup.py
tox.ini
.github/workflows/test_and_deploy.yml
.idea/.gitignore
.idea/misc.xml
.idea/modules.xml
.idea/napari-IDS.iml
.idea/vcs.xml
.idea/inspectionProfiles/profiles_settings.xml
.napari/DESCRIPTION.md
bin/ids_packages
src/napari_IDS.egg-info/PKG-INFO
src/napari_IDS.egg-info/SOURCES.txt
src/napari_IDS.egg-info/dependency_links.txt
src/napari_IDS.egg-info/entry_points.txt
src/napari_IDS.egg-info/requires.txt
src/napari_IDS.egg-info/top_level.txt
src/napari_ids/__init__.py
src/napari_ids/_widget.py
src/napari_ids/napari.yaml
src/napari_ids/video_ui.py
src/napari_ids/_tests/__init__.py
src/napari_ids/_tests/test_dock_widget.py
src/napari_ids/_tests/test_reader.py
src/napari_ids/_tests/test_sample_data.py
src/napari_ids/_tests/test_widget.py
src/napari_ids/_tests/test_writer.py
src/napari_ids/img/logo_ids.jpg
src/napari_ids/stylesheets/widget_live.css